sitecustomize.py
retracesoftware_autoenable-0.1.0.dist-info/licenses/LICENSE
retracesoftware_autoenable-0.1.0.dist-info/METADATA
retracesoftware_autoenable-0.1.0.dist-info/WHEEL
retracesoftware_autoenable-0.1.0.dist-info/top_level.txt
retracesoftware_autoenable-0.1.0.dist-info/RECORD
