Metadata-Version: 2.4
Name: retracesoftware_autoenable
Version: 0.1.0
Summary: Auto-enable retracesoftware instrumentation
License: Apache-2.0
Requires-Python: >=3.11
License-File: LICENSE
Requires-Dist: retracesoftware_proxy
Dynamic: license-file
